odoo/addons/request_document_purchase_request/README.rst
odoo/addons/request_document_purchase_request/__init__.py
odoo/addons/request_document_purchase_request/__manifest__.py
odoo/addons/request_document_purchase_request/i18n/request_document_purchase_request.pot
odoo/addons/request_document_purchase_request/models/__init__.py
odoo/addons/request_document_purchase_request/models/purchase_request.py
odoo/addons/request_document_purchase_request/models/request_document.py
odoo/addons/request_document_purchase_request/models/request_order.py
odoo/addons/request_document_purchase_request/models/res_company.py
odoo/addons/request_document_purchase_request/models/res_config_settings.py
odoo/addons/request_document_purchase_request/readme/CONTRIBUTORS.rst
odoo/addons/request_document_purchase_request/readme/DESCRIPTION.rst
odoo/addons/request_document_purchase_request/static/description/icon.png
odoo/addons/request_document_purchase_request/static/description/index.html
odoo/addons/request_document_purchase_request/tests/__init__.py
odoo/addons/request_document_purchase_request/tests/test_request_document_purchase_request.py
odoo/addons/request_document_purchase_request/views/purchase_request_view.xml
odoo/addons/request_document_purchase_request/views/request_order_view.xml
odoo/addons/request_document_purchase_request/views/res_config_settings_views.xml
odoo_addon_request_document_purchase_request-18.0.1.0.1.dist-info/METADATA
odoo_addon_request_document_purchase_request-18.0.1.0.1.dist-info/WHEEL
odoo_addon_request_document_purchase_request-18.0.1.0.1.dist-info/top_level.txt
odoo_addon_request_document_purchase_request-18.0.1.0.1.dist-info/RECORD
